stockman/__init__.py
stockman/apis/__init__.py
stockman/apis/tushare.py
stockman/configs/__init__.py
stockman/configs/apis.py
stockman/configs/dbconfig.py
stockman/tasks/__init__.py
stockman/tasks/initdata.py
stockman/tasks/install.py
stockman/tasks/set_times_limit.py
stockman/tasks/update.py
stockman/utils/__init__.py
stockman/utils/contants.py
stockman/utils/db.py
stockman/utils/exceptions.py
stockman/utils/timeslimit.py
stockman-0.0.2.dist-info/LICENSE
stockman-0.0.2.dist-info/METADATA
stockman-0.0.2.dist-info/WHEEL
stockman-0.0.2.dist-info/top_level.txt
stockman-0.0.2.dist-info/RECORD
