Metadata-Version: 2.1
Name: stockman
Version: 0.0.2
Summary: A股量化数据工具
Home-page: https://github.com/sml2h3/stockman
Author: sml2h3
Classifier: Programming Language :: Python :: 3
Classifier: License :: OSI Approved :: MIT License
Classifier: Operating System :: OS Independent
Requires-Python: <=3.11
License-File: LICENSE
Requires-Dist: pymysql
Requires-Dist: pyyaml
Requires-Dist: tushare
